netbox_storage/__init__.py
netbox_storage/api/nested_serializers.py
netbox_storage/api/serializers.py
netbox_storage/api/urls.py
netbox_storage/api/views.py
netbox_storage/apps.py
netbox_storage/choices.py
netbox_storage/filters/__init__.py
netbox_storage/filters/drive.py
netbox_storage/filters/filesystem.py
netbox_storage/filters/linux_device.py
netbox_storage/filters/logical_volume.py
netbox_storage/filters/mounted_volume.py
netbox_storage/filters/partition.py
netbox_storage/filters/physical_volume.py
netbox_storage/filters/template_configuration_drive.py
netbox_storage/filters/volume_group.py
netbox_storage/forms/__init__.py
netbox_storage/forms/drive.py
netbox_storage/forms/filesystem.py
netbox_storage/forms/linux_device.py
netbox_storage/forms/logical_volume.py
netbox_storage/forms/model_forms.py
netbox_storage/forms/mounted_volume.py
netbox_storage/forms/partition.py
netbox_storage/forms/physical_volume.py
netbox_storage/forms/simple.py
netbox_storage/forms/template.py
netbox_storage/forms/volume_group.py
netbox_storage/migrations/0001_initial.py
netbox_storage/migrations/__init__.py
netbox_storage/models.py
netbox_storage/navigation.py
netbox_storage/search.py
netbox_storage/tables/__init__.py
netbox_storage/tables/drive.py
netbox_storage/tables/filesystem.py
netbox_storage/tables/linux_device.py
netbox_storage/tables/logical_volume.py
netbox_storage/tables/mounted_volume.py
netbox_storage/tables/partition.py
netbox_storage/tables/physical_volume.py
netbox_storage/tables/volume_group.py
netbox_storage/template_content.py
netbox_storage/templates/netbox_storage/drive/base.html
netbox_storage/templates/netbox_storage/drive/child.html
netbox_storage/templates/netbox_storage/drive/partition.html
netbox_storage/templates/netbox_storage/drive.html
netbox_storage/templates/netbox_storage/drive_create.html
netbox_storage/templates/netbox_storage/filesystem.html
netbox_storage/templates/netbox_storage/inc/linuxvolume_box.html
netbox_storage-0.0.0.0.946.dist-info/WHEEL
netbox_storage-0.0.0.0.946.dist-info/METADATA
netbox_storage-0.0.0.0.946.dist-info/RECORD
