Metadata-Version: 2.1
Name: netbox-storage
Version: 0.0.0.0.946
Summary: Netbox Storage Plugin
Author: Tim Rhomberg
Author-email: timrhomberg@hotmail.com
Requires-Python: >=3.7,<4.0
Classifier: Programming Language :: Python :: 3
Classifier: Programming Language :: Python :: 3.7
Classifier: Programming Language :: Python :: 3.8
Classifier: Programming Language :: Python :: 3.9
Classifier: Programming Language :: Python :: 3.10
Classifier: Programming Language :: Python :: 3.11
